riverapi/__init__.py
riverapi/auth.py
riverapi/defaults.py
riverapi/logger.py
riverapi/main.py
riverapi/version.py
riverapi/utils/__init__.py
riverapi/utils/fileio.py
riverapi/utils/terminal.py
riverapi-0.0.21.dist-info/LICENSE
riverapi-0.0.21.dist-info/METADATA
riverapi-0.0.21.dist-info/WHEEL
riverapi-0.0.21.dist-info/top_level.txt
riverapi-0.0.21.dist-info/RECORD
