Metadata-Version: 2.1
Name: riverapi
Version: 0.0.21
Summary: Python client for interacting with online-ml river server
Home-page: https://github.com/vsoch/riverapi
Author: Vanessa Sochat
Author-email: vsoch@users.noreply.github.com
Maintainer: Vanessa Sochat
License: LICENSE
Keywords: river,online-ml,api client
Platform: UNKNOWN
Classifier: Intended Audience :: Science/Research
Classifier: Intended Audience :: Developers
Classifier: License :: OSI Approved :: Mozilla Public License 2.0 (MPL 2.0)
Classifier: Programming Language :: C
Classifier: Programming Language :: Python
Classifier: Topic :: Software Development
Classifier: Topic :: Scientific/Engineering
Classifier: Operating System :: Unix
Classifier: Programming Language :: Python :: 3.8
License-File: LICENSE
Requires-Dist: dill
Requires-Dist: requests
Requires-Dist: river
Provides-Extra: all
Requires-Dist: dill ; extra == 'all'
Requires-Dist: requests ; extra == 'all'
Requires-Dist: river ; extra == 'all'
Requires-Dist: pytest (>=4.6.2) ; extra == 'all'
